<?xml version="1.0"?>
<object name="portal_catalog">
    <index name="noticeUrl" meta_type="FieldIndex">
        <indexed_attr value="noticeUrl"/>
    </index>
    <column value="noticeUrl"/>

    <index name="noticeId" meta_type="FieldIndex">
        <indexed_attr value="noticeId"/>
    </index>
    <column value="noticeId"/>

    <index name="noticeName" meta_type="FieldIndex">
        <indexed_attr value="noticeName"/>
    </index>
    <column value="noticeName"/>

    <index name="govDepartment" meta_type="FieldIndex">
        <indexed_attr value="govDepartment"/>
    </index>
    <column value="govDepartment"/>
</object>
